{
  "project_info": {
    "project_number": "332967200175",
    "firebase_url": "https://demoapp-3e717.firebaseio.com",
    "project_id": "demoapp-3e717",
    "storage_bucket": "demoapp-3e717.appspot.com"
  },
  "client": [
    {
      "client_info": {
        "mobilesdk_app_id": "1:332967200175:android:8fe4f3b9579593cb8fdb5a",
        "android_client_info": {
          "package_name": "com.arpitverma621.demoapp"
        }
      },
      "oauth_client": [
        {
          "client_id": "332967200175-d7v0sm5d3kmpgk560f1efkfhjfoeo791.apps.googleusercontent.com",
          "client_type": 3
        }
      ],
      "api_key": [
        {
          "current_key": "AIzaSyDHNc2Zlst5rd8VW72jdvQ7VW8slFyBcjk"
        }
      ],
      "services": {
        "appinvite_service": {
          "other_platform_oauth_client": [
            {
              "client_id": "332967200175-d7v0sm5d3kmpgk560f1efkfhjfoeo791.apps.googleusercontent.com",
              "client_type": 3
            }
          ]
        }
      }
    },
    {
      "client_info": {
        "mobilesdk_app_id": "1:332967200175:android:230cab6e799a887e8fdb5a",
        "android_client_info": {
          "package_name": "com.arpitverma621.firebaseauthentication"
        }
      },
      "oauth_client": [
        {
          "client_id": "332967200175-d7v0sm5d3kmpgk560f1efkfhjfoeo791.apps.googleusercontent.com",
          "client_type": 3
        }
      ],
      "api_key": [
        {
          "current_key": "AIzaSyDHNc2Zlst5rd8VW72jdvQ7VW8slFyBcjk"
        }
      ],
      "services": {
        "appinvite_service": {
          "other_platform_oauth_client": [
            {
              "client_id": "332967200175-d7v0sm5d3kmpgk560f1efkfhjfoeo791.apps.googleusercontent.com",
              "client_type": 3
            }
          ]
        }
      }
    }
  ],
  "configuration_version": "1"
}